open3d/__init__.py
open3d/web_visualizer.py
open3d/ml/__init__.py
open3d/ml/configs.py
open3d/ml/datasets.py
open3d/ml/utils.py
open3d/ml/vis.py
open3d/ml/contrib/__init__.py
open3d/ml/tf/__init__.py
open3d/ml/tf/configs.py
open3d/ml/tf/dataloaders.py
open3d/ml/tf/datasets.py
open3d/ml/tf/models.py
open3d/ml/tf/modules.py
open3d/ml/tf/pipelines.py
open3d/ml/tf/vis.py
open3d/ml/tf/layers/__init__.py
open3d/ml/tf/ops/__init__.py
open3d/ml/tf/python/layers/convolutions.py
open3d/ml/tf/python/layers/neighbor_search.py
open3d/ml/tf/python/layers/voxel_pooling.py
open3d/ml/tf/python/ops/gradients.py
open3d/ml/tf/python/ops/lib.py
open3d/ml/tf/python/ops/ops.py.in
open3d/ml/torch/__init__.py
open3d/ml/torch/configs.py
open3d/ml/torch/dataloaders.py
open3d/ml/torch/datasets.py
open3d/ml/torch/models.py
open3d/ml/torch/modules.py
open3d/ml/torch/pipelines.py
open3d/ml/torch/vis.py
open3d/ml/torch/classes/__init__.py
open3d/ml/torch/classes/ragged_tensor.py
open3d/ml/torch/layers/__init__.py
open3d/ml/torch/ops/__init__.py
open3d/ml/torch/python/ops.py.in
open3d/ml/torch/python/return_types.py.in
open3d/ml/torch/python/layers/convolutions.py
open3d/ml/torch/python/layers/neighbor_search.py
open3d/ml/torch/python/layers/voxel_pooling.py
open3d/visualization/__init__.py
open3d/visualization/__main__.py
open3d/visualization/_external_visualizer.py
open3d/visualization/async_event_loop.py
open3d/visualization/draw.py
open3d/visualization/draw_plotly.py
open3d/visualization/to_mitsuba.py
open3d/visualization/tensorboard_plugin/colormap.py
open3d/visualization/tensorboard_plugin/labellut.py
open3d/visualization/tensorboard_plugin/metadata.py
open3d/visualization/tensorboard_plugin/plugin.py
open3d/visualization/tensorboard_plugin/plugin_data.proto
open3d/visualization/tensorboard_plugin/plugin_data_pb2.py
open3d/visualization/tensorboard_plugin/summary.py
open3d/visualization/tensorboard_plugin/util.py
open3d/visualization/tensorboard_plugin/frontend/index.js
gismath_open3d-0.0.2.dist-info/LICENSE.txt
gismath_open3d-0.0.2.dist-info/METADATA
gismath_open3d-0.0.2.dist-info/WHEEL
gismath_open3d-0.0.2.dist-info/entry_points.txt
gismath_open3d-0.0.2.dist-info/top_level.txt
gismath_open3d-0.0.2.dist-info/RECORD
